mixinputs/__init__.py
mixinputs/commands.py
mixinputs/gpu_input_batch.py
mixinputs/gpu_model_runner.py
mixinputs/vllm_patch.py
mixinputs/scripts/__init__.py
mixinputs/scripts/reward_aime.py
mixinputs-0.1.1.dist-info/LICENSE
mixinputs-0.1.1.dist-info/METADATA
mixinputs-0.1.1.dist-info/WHEEL
mixinputs-0.1.1.dist-info/entry_points.txt
mixinputs-0.1.1.dist-info/top_level.txt
mixinputs-0.1.1.dist-info/RECORD
