Metadata-Version: 2.1
Name: mixinputs
Version: 0.1.1
Summary: Mixture of Inputs Patch for vLLM
Home-page: https://github.com/EvanZhuang/mixinputs
Author: Yufan Zhuang
Author-email: y5zhuang@ucsd.edu
License: Apache License 2.0
Classifier: Development Status :: 2 - Pre-Alpha
Classifier: Intended Audience :: Developers
Classifier: Natural Language :: English
License-File: LICENSE
Requires-Dist: vllm>=0.8.5
